{
  "db_name": "PostgreSQL",
  "query": "\n            SELECT t.id, t.slug, t.name\n            FROM tags t\n            INNER JOIN post_tags pt ON pt.tag_id = t.id\n            WHERE pt.post_id = $1\n            ORDER BY t.name ASC\n            ",
  "describe": {
    "columns": [
      {
        "ordinal": 0,
        "name": "id",
        "type_info": "Uuid"
      },
      {
        "ordinal": 1,
        "name": "slug",
        "type_info": "Text"
      },
      {
        "ordinal": 2,
        "name": "name",
        "type_info": "Text"
      }
    ],
    "parameters": {
      "Left": [
        "Uuid"
      ]
    },
    "nullable": [
      false,
      false,
      false
    ]
  },
  "hash": "0cb7826b1518302046ac81f607152f9aaa886c850fce82f7201fa250e01e57ff"
}
